render_engine_theme_kjaymiller/__init__.py
render_engine_theme_kjaymiller/kjaymiller.py
render_engine_theme_kjaymiller/tailwind_colors.py
render_engine_theme_kjaymiller/utils.py
render_engine_theme_kjaymiller/static/css/microblog_archive.css
render_engine_theme_kjaymiller/static/css/pygments.css
render_engine_theme_kjaymiller/static/css/tailwind.css
render_engine_theme_kjaymiller/static/files/cloudanimation.svg
render_engine_theme_kjaymiller/static/files/search.svg
render_engine_theme_kjaymiller/static/fonts/mononoki Bold Italic Nerd Font Complete.ttf
render_engine_theme_kjaymiller/static/fonts/mononoki Bold Nerd Font Complete.ttf
render_engine_theme_kjaymiller/static/fonts/mononoki Italic Nerd Font Complete.ttf
render_engine_theme_kjaymiller/static/fonts/mononoki-Regular Nerd Font Complete.ttf
render_engine_theme_kjaymiller/static/images/social_card_base.jpg
render_engine_theme_kjaymiller/templates/blog.html
render_engine_theme_kjaymiller/templates/blog_list.html
render_engine_theme_kjaymiller/templates/index.html
render_engine_theme_kjaymiller/templates/page.html
render_engine_theme_kjaymiller/templates/search.js
render_engine_theme_kjaymiller/templates/kjaymiller_com/_head.html
render_engine_theme_kjaymiller/templates/kjaymiller_com/components/_archive.html
render_engine_theme_kjaymiller/templates/kjaymiller_com/components/_base.html
render_engine_theme_kjaymiller/templates/kjaymiller_com/components/_footer.html
render_engine_theme_kjaymiller/templates/kjaymiller_com/components/_header.html
render_engine_theme_kjaymiller/templates/kjaymiller_com/components/_og_card.html
render_engine_theme_kjaymiller/templates/kjaymiller_com/components/_pagination.html
render_engine_theme_kjaymiller/templates/kjaymiller_com/components/social-cards.html
render_engine_theme_kjaymiller-2025.6.1.dist-info/METADATA
render_engine_theme_kjaymiller-2025.6.1.dist-info/WHEEL
render_engine_theme_kjaymiller-2025.6.1.dist-info/top_level.txt
render_engine_theme_kjaymiller-2025.6.1.dist-info/RECORD
