Metadata-Version: 2.4
Name: render-engine-theme-kjaymiller
Version: 2025.6.1
Summary: This is a theme based on the design of kjaymiller.com at the time
Project-URL: homepage, https://kjaymiller.github.io/render_engine_theme_kjaymiller
Project-URL: repository, https://github.com/kjaymiller/render-engine-theme-kjaymiller
Project-URL: documentation, https://github.io/kjaymiller/render-engine-theme-kjaymille
Requires-Dist: jinja2
Requires-Dist: render-engine-tailwindcss>=2024.1.1a2
Requires-Dist: render-engine-markdown
Requires-Dist: render-engine>=2025.6.1a1
Provides-Extra: dev
Requires-Dist: axe-playwright-python; extra == "dev"
Requires-Dist: playwright; extra == "dev"
Requires-Dist: pytest; extra == "dev"
Requires-Dist: pytest-mock; extra == "dev"
Requires-Dist: pytest-playwright; extra == "dev"
Requires-Dist: ruff; extra == "dev"
